{"_default": {"1": {"vo": "59148", "va": "5156153", "o": "88.00", "h": "88.25", "c": "87.50", "d": "20171013", "l": "87.00"}, "2": {"vo": "53712", "va": "4673691", "o": "86.75", "h": "87.75", "c": "87.75", "d": "20171012", "l": "86.50"}, "3": {"vo": "24370", "va": "2139352", "o": "88.25", "h": "88.50", "c": "86.75", "d": "20171011", "l": "86.00"}, "4": {"vo": "69480", "va": "6107609", "o": "87.75", "h": "88.25", "c": "88.25", "d": "20171010", "l": "87.50"}, "5": {"vo": "44078", "va": "3836301", "o": "86.25", "h": "87.75", "c": "87.75", "d": "20171009", "l": "86.25"}, "6": {"vo": "27705", "va": "2400137", "o": "86.75", "h": "87.25", "c": "87.00", "d": "20171006", "l": "86.50"}, "7": {"vo": "10618", "va": "919643", "o": "86.50", "h": "86.75", "c": "86.75", "d": "20171005", "l": "86.50"}, "8": {"vo": "49807", "va": "4294503", "o": "86.50", "h": "86.50", "c": "86.50", "d": "20171004", "l": "86.00"}, "9": {"vo": "37881", "va": "3279411", "o": "86.50", "h": "86.75", "c": "86.50", "d": "20171003", "l": "86.50"}, "10": {"vo": "10268", "va": "886963", "o": "85.00", "h": "86.50", "c": "86.50", "d": "20171002", "l": "85.00"}, "11": {"vo": "18078", "va": "1553057", "o": "85.50", "h": "86.25", "c": "86.00", "d": "20170929", "l": "85.00"}, "12": {"vo": "25361", "va": "2166923", "o": "85.50", "h": "85.75", "c": "85.50", "d": "20170928", "l": "85.00"}, "13": {"vo": "11594", "va": "990358", "o": "85.75", "h": "86.00", "c": "85.25", "d": "20170927", "l": "84.25"}, "14": {"vo": "10771", "va": "921464", "o": "85.00", "h": "86.00", "c": "85.75", "d": "20170926", "l": "84.50"}, "15": {"vo": "89537", "va": "7644216", "o": "85.50", "h": "86.00", "c": "85.00", "d": "20170925", "l": "85.00"}, "16": {"vo": "44577", "va": "3828569", "o": "85.75", "h": "86.00", "c": "85.50", "d": "20170922", "l": "85.00"}, "17": {"vo": "215797", "va": "18428010", "o": "85.75", "h": "85.75", "c": "85.75", "d": "20170921", "l": "85.00"}, "18": {"vo": "14764", "va": "1265394", "o": "86.00", "h": "86.00", "c": "85.75", "d": "20170920", "l": "85.00"}, "19": {"vo": "44489", "va": "3793104", "o": "84.75", "h": "85.75", "c": "85.75", "d": "20170919", "l": "84.75"}, "20": {"vo": "9698", "va": "819814", "o": "84.75", "h": "85.00", "c": "85.00", "d": "20170918", "l": "83.50"}, "21": {"vo": "5623", "va": "474080", "o": "83.75", "h": "84.75", "c": "84.75", "d": "20170915", "l": "83.50"}, "22": {"vo": "227263", "va": "19238157", "o": "85.00", "h": "85.00", "c": "84.00", "d": "20170914", "l": "84.00"}, "23": {"vo": "3260", "va": "276564", "o": "85.00", "h": "85.00", "c": "85.00", "d": "20170913", "l": "84.25"}, "24": {"vo": "153886", "va": "12920674", "o": "83.75", "h": "85.00", "c": "85.00", "d": "20170912", "l": "83.50"}, "25": {"vo": "63458", "va": "5278937", "o": "83.00", "h": "84.00", "c": "83.25", "d": "20170911", "l": "82.50"}, "26": {"vo": "29202", "va": "2454837", "o": "84.50", "h": "84.50", "c": "82.50", "d": "20170908", "l": "82.50"}, "27": {"vo": "9895", "va": "839193", "o": "84.75", "h": "85.00", "c": "84.50", "d": "20170907", "l": "84.50"}, "28": {"vo": "78882", "va": "6721283", "o": "85.25", "h": "85.25", "c": "85.00", "d": "20170906", "l": "84.75"}, "29": {"vo": "14701", "va": "1247251", "o": "84.75", "h": "85.50", "c": "85.50", "d": "20170905", "l": "84.50"}, "30": {"vo": "40233", "va": "3417381", "o": "84.75", "h": "85.25", "c": "85.25", "d": "20170904", "l": "84.50"}, "31": {"vo": "9055", "va": "775688", "o": "85.50", "h": "86.00", "c": "84.50", "d": "20170901", "l": "84.50"}, "32": {"vo": "66410", "va": "5657660", "o": "85.50", "h": "85.50", "c": "85.50", "d": "20170831", "l": "84.00"}, "33": {"vo": "11749", "va": "996496", "o": "84.50", "h": "85.75", "c": "85.50", "d": "20170830", "l": "84.50"}, "34": {"vo": "8076", "va": "684929", "o": "84.00", "h": "85.00", "c": "85.00", "d": "20170829", "l": "84.00"}, "35": {"vo": "162162", "va": "13620740", "o": "84.75", "h": "84.75", "c": "84.00", "d": "20170828", "l": "82.00"}, "36": {"vo": "35008", "va": "2951516", "o": "84.75", "h": "84.75", "c": "84.25", "d": "20170825", "l": "84.00"}, "37": {"vo": "20058", "va": "1701929", "o": "85.00", "h": "85.00", "c": "84.75", "d": "20170824", "l": "84.50"}, "38": {"vo": "19357", "va": "1663594", "o": "86.00", "h": "86.00", "c": "85.00", "d": "20170823", "l": "85.00"}, "39": {"vo": "11749", "va": "1009980", "o": "85.75", "h": "86.00", "c": "85.75", "d": "20170822", "l": "85.50"}, "40": {"vo": "34240", "va": "2881611", "o": "84.75", "h": "85.50", "c": "85.50", "d": "20170821", "l": "84.00"}, "41": {"vo": "20325", "va": "1718871", "o": "85.75", "h": "85.75", "c": "84.50", "d": "20170818", "l": "84.00"}, "42": {"vo": "24643", "va": "2128980", "o": "87.00", "h": "87.00", "c": "85.50", "d": "20170817", "l": "85.50"}, "43": {"vo": "38818", "va": "3374641", "o": "86.25", "h": "87.25", "c": "87.00", "d": "20170816", "l": "86.25"}, "44": {"vo": "44458", "va": "3837878", "o": "85.75", "h": "87.00", "c": "86.25", "d": "20170815", "l": "85.00"}, "45": {"vo": "17868", "va": "1531259", "o": "85.25", "h": "86.00", "c": "85.75", "d": "20170814", "l": "85.25"}, "46": {"vo": "51212", "va": "4360662", "o": "85.50", "h": "85.50", "c": "85.00", "d": "20170811", "l": "84.75"}, "47": {"vo": "55906", "va": "4777369", "o": "85.25", "h": "86.00", "c": "85.50", "d": "20170810", "l": "84.00"}, "48": {"vo": "37659", "va": "3210823", "o": "84.25", "h": "86.00", "c": "85.00", "d": "20170809", "l": "84.25"}, "49": {"vo": "93346", "va": "7861369", "o": "85.00", "h": "85.00", "c": "84.50", "d": "20170808", "l": "84.00"}, "50": {"vo": "35805", "va": "3018745", "o": "84.75", "h": "84.75", "c": "84.25", "d": "20170807", "l": "84.25"}, "51": {"vo": "13536", "va": "1140434", "o": "84.00", "h": "84.50", "c": "84.50", "d": "20170804", "l": "84.00"}, "52": {"vo": "21923", "va": "1849057", "o": "84.25", "h": "84.50", "c": "84.25", "d": "20170803", "l": "83.50"}, "53": {"vo": "55031", "va": "4645033", "o": "84.50", "h": "84.50", "c": "84.50", "d": "20170802", "l": "84.25"}, "54": {"vo": "29948", "va": "2517652", "o": "84.00", "h": "84.50", "c": "84.25", "d": "20170801", "l": "83.75"}, "55": {"vo": "45419", "va": "3798792", "o": "84.00", "h": "84.00", "c": "83.75", "d": "20170731", "l": "83.50"}, "56": {"vo": "8772", "va": "732720", "o": "83.75", "h": "83.75", "c": "83.50", "d": "20170728", "l": "83.50"}, "57": {"vo": "36256", "va": "3036934", "o": "83.75", "h": "84.00", "c": "83.50", "d": "20170727", "l": "83.50"}, "58": {"vo": "16438", "va": "1372470", "o": "83.25", "h": "83.75", "c": "83.50", "d": "20170726", "l": "83.25"}, "59": {"vo": "26064", "va": "2156354", "o": "82.75", "h": "83.00", "c": "83.00", "d": "20170725", "l": "82.50"}, "60": {"vo": "12885", "va": "1064927", "o": "85.00", "h": "85.00", "c": "82.50", "d": "20170724", "l": "82.50"}, "61": {"vo": "21940", "va": "1818083", "o": "83.00", "h": "83.25", "c": "82.50", "d": "20170721", "l": "82.00"}, "62": {"vo": "20187", "va": "1693936", "o": "84.00", "h": "84.375", "c": "83.00", "d": "20170720", "l": "83.00"}, "63": {"vo": "58334", "va": "4818102", "o": "81.00", "h": "85.00", "c": "84.50", "d": "20170719", "l": "81.00"}, "64": {"vo": "16230", "va": "1318318", "o": "81.25", "h": "81.50", "c": "81.25", "d": "20170718", "l": "81.00"}, "65": {"vo": "35894", "va": "2915719", "o": "81.00", "h": "81.50", "c": "81.25", "d": "20170717", "l": "81.00"}, "66": {"vo": "47649", "va": "3860989", "o": "80.50", "h": "81.50", "c": "81.00", "d": "20170714", "l": "80.50"}, "67": {"vo": "17162", "va": "1392023", "o": "81.00", "h": "81.50", "c": "80.75", "d": "20170713", "l": "80.75"}, "68": {"vo": "194179", "va": "15393844", "o": "79.00", "h": "81.50", "c": "80.50", "d": "20170712", "l": "78.75"}, "69": {"vo": "7618", "va": "600729", "o": "78.75", "h": "79.00", "c": "79.00", "d": "20170711", "l": "78.50"}, "70": {"vo": "103049", "va": "8140010", "o": "79.00", "h": "79.25", "c": "79.00", "d": "20170710", "l": "78.50"}, "71": {"vo": "8111", "va": "638816", "o": "78.75", "h": "79.00", "c": "79.00", "d": "20170707", "l": "78.75"}, "72": {"vo": "7546", "va": "594353", "o": "79.00", "h": "79.00", "c": "78.75", "d": "20170706", "l": "78.50"}, "73": {"vo": "44137", "va": "3479294", "o": "79.00", "h": "79.00", "c": "79.00", "d": "20170705", "l": "78.75"}, "74": {"vo": "23684", "va": "1867759", "o": "78.75", "h": "79.00", "c": "78.75", "d": "20170704", "l": "78.75"}, "75": {"vo": "19630", "va": "1545559", "o": "78.75", "h": "79.00", "c": "78.75", "d": "20170703", "l": "78.25"}, "76": {"vo": "16837", "va": "1324457", "o": "79.00", "h": "79.00", "c": "78.75", "d": "20170630", "l": "78.25"}, "77": {"vo": "74236", "va": "5828601", "o": "78.50", "h": "79.00", "c": "78.25", "d": "20170629", "l": "78.00"}, "78": {"vo": "16756", "va": "1310515", "o": "78.00", "h": "78.50", "c": "78.50", "d": "20170628", "l": "78.00"}, "79": {"vo": "41890", "va": "3282496", "o": "78.25", "h": "78.75", "c": "78.00", "d": "20170627", "l": "78.00"}, "80": {"vo": "112788", "va": "8817692", "o": "78.50", "h": "78.50", "c": "78.25", "d": "20170626", "l": "78.00"}, "81": {"vo": "23962", "va": "1874804", "o": "78.75", "h": "78.75", "c": "78.25", "d": "20170623", "l": "78.00"}, "82": {"vo": "1579241", "va": "123199859", "o": "78.25", "h": "78.50", "c": "78.00", "d": "20170622", "l": "78.00"}, "83": {"vo": "107399", "va": "8425101", "o": "79.00", "h": "79.00", "c": "78.25", "d": "20170621", "l": "78.25"}, "84": {"vo": "76425", "va": "6037380", "o": "79.25", "h": "79.25", "c": "79.00", "d": "20170620", "l": "78.75"}, "85": {"vo": "169599", "va": "13434496", "o": "79.75", "h": "79.75", "c": "79.00", "d": "20170619", "l": "79.00"}, "86": {"vo": "357433", "va": "28296317", "o": "79.50", "h": "79.50", "c": "79.25", "d": "20170616", "l": "79.00"}, "87": {"vo": "187299", "va": "14880943", "o": "80.00", "h": "80.00", "c": "79.25", "d": "20170615", "l": "79.25"}, "88": {"vo": "406831", "va": "32403071", "o": "79.25", "h": "80.00", "c": "79.75", "d": "20170614", "l": "79.25"}, "89": {"vo": "1903799", "va": "149734533", "o": "78.50", "h": "79.25", "c": "79.00", "d": "20170613", "l": "78.50"}, "90": {"vo": "111614", "va": "9711043", "o": "87.50", "h": "87.75", "c": "87.00", "d": "20171016", "l": "87.00"}, "91": {"vo": "15926", "va": "1391014", "o": "87.00", "h": "87.50", "c": "87.25", "d": "20171017", "l": "87.00"}, "92": {"vo": "21586", "va": "1884484", "o": "88.00", "h": "88.25", "c": "88.00", "d": "20171020", "l": "87.00"}, "93": {"vo": "20027", "va": "1758729", "o": "87.75", "h": "88.00", "c": "88.00", "d": "20171019", "l": "87.75"}, "94": {"vo": "23687", "va": "2072187", "o": "87.50", "h": "87.75", "c": "87.50", "d": "20171018", "l": "87.25"}, "95": {"vo": "6953", "va": "607718", "o": "87.75", "h": "87.75", "c": "87.25", "d": "20171024", "l": "87.00"}, "96": {"vo": "28740", "va": "2521762", "o": "87.75", "h": "88.00", "c": "88.00", "d": "20171023", "l": "87.50"}, "97": {"vo": "119100", "va": "10375320", "o": "87.50", "h": "87.50", "c": "86.75", "d": "20171025", "l": "86.25"}, "98": {"vo": "13025", "va": "1134917", "o": "87.00", "h": "87.25", "c": "87.00", "d": "20171026", "l": "86.25"}, "99": {"vo": "55790", "va": "4866082", "o": "87.50", "h": "87.75", "c": "87.75", "d": "20171027", "l": "86.75"}, "100": {"vo": "31515", "va": "2769559", "o": "87.75", "h": "88.25", "c": "88.00", "d": "20171030", "l": "87.50"}, "101": {"vo": "28202", "va": "2494684", "o": "88.00", "h": "88.75", "c": "88.75", "d": "20171031", "l": "88.00"}, "102": {"vo": "81519", "va": "7291828", "o": "89.00", "h": "89.50", "c": "89.50", "d": "20171101", "l": "89.00"}, "103": {"vo": "28761", "va": "2563944", "o": "89.75", "h": "89.75", "c": "89.00", "d": "20171103", "l": "88.00"}, "104": {"vo": "23742", "va": "2128638", "o": "89.25", "h": "90.00", "c": "89.50", "d": "20171102", "l": "89.25"}, "105": {"vo": "81072", "va": "7218556", "o": "89.00", "h": "89.50", "c": "89.50", "d": "20171106", "l": "88.50"}, "106": {"vo": "12188", "va": "1092442", "o": "89.50", "h": "89.75", "c": "89.75", "d": "20171107", "l": "89.25"}, "107": {"vo": "18359", "va": "1646960", "o": "89.75", "h": "90.00", "c": "89.25", "d": "20171108", "l": "89.25"}, "108": {"vo": "28441", "va": "2506113", "o": "89.00", "h": "89.00", "c": "88.25", "d": "20171110", "l": "87.25"}, "109": {"vo": "45542", "va": "4045632", "o": "89.50", "h": "89.50", "c": "88.50", "d": "20171109", "l": "88.50"}, "110": {"vo": "46659", "va": "4130010", "o": "88.50", "h": "89.00", "c": "88.00", "d": "20171113", "l": "87.25"}, "111": {"vo": "227143", "va": "20153574", "o": "88.25", "h": "89.00", "c": "88.75", "d": "20171114", "l": "88.00"}, "112": {"vo": "59829", "va": "5272946", "o": "88.50", "h": "89.00", "c": "88.00", "d": "20171115", "l": "87.00"}, "113": {"vo": "28516", "va": "2509538", "o": "87.50", "h": "88.25", "c": "88.25", "d": "20171116", "l": "87.50"}, "114": {"vo": "36576", "va": "3219544", "o": "88.50", "h": "88.50", "c": "88.00", "d": "20171117", "l": "87.75"}, "115": {"vo": "30301", "va": "2682051", "o": "88.50", "h": "88.75", "c": "88.50", "d": "20171121", "l": "88.25"}, "116": {"vo": "17853", "va": "1572125", "o": "88.00", "h": "88.25", "c": "88.25", "d": "20171120", "l": "87.75"}, "117": {"vo": "28126", "va": "2486077", "o": "88.50", "h": "88.50", "c": "88.25", "d": "20171122", "l": "88.00"}, "118": {"vo": "45562", "va": "4031995", "o": "88.25", "h": "88.75", "c": "88.50", "d": "20171124", "l": "88.25"}, "119": {"vo": "23295", "va": "2060987", "o": "88.00", "h": "88.50", "c": "88.50", "d": "20171123", "l": "88.00"}, "120": {"vo": "39921", "va": "3585402", "o": "89.00", "h": "90.25", "c": "90.25", "d": "20171129", "l": "88.75"}, "121": {"vo": "62502", "va": "5534549", "o": "88.50", "h": "89.00", "c": "89.00", "d": "20171128", "l": "88.00"}, "122": {"vo": "31282", "va": "2763043", "o": "88.25", "h": "88.50", "c": "88.50", "d": "20171127", "l": "88.00"}, "123": {"vo": "46036", "va": "4077197", "o": "88.50", "h": "89.75", "c": "88.50", "d": "20171201", "l": "88.00"}, "124": {"vo": "457040", "va": "40799063", "o": "91.00", "h": "91.25", "c": "88.50", "d": "20171130", "l": "88.50"}, "125": {"vo": "14905", "va": "1329915", "o": "90.75", "h": "90.75", "c": "89.25", "d": "20171205", "l": "88.50"}, "126": {"vo": "27710", "va": "2479392", "o": "89.00", "h": "90.75", "c": "89.75", "d": "20171204", "l": "88.00"}, "127": {"vo": "27912", "va": "2514659", "o": "90.00", "h": "91.00", "c": "91.00", "d": "20171208", "l": "89.00"}, "128": {"vo": "75224", "h": "90.00", "va": "6734837", "o": "89.00", "c": "89.75", "d": "20171207", "l": "88.75"}, "129": {"c": "89.00", "vo": "32401", "va": "2885087", "o": "89.50", "h": "89.50", "d": "20171206", "l": "88.50"}}}